neuro_mf/__init__.py
neuro_mf/constant.py
neuro_mf/config/__init__.py
neuro_mf-0.0.5.dist-info/LICENSE
neuro_mf-0.0.5.dist-info/METADATA
neuro_mf-0.0.5.dist-info/WHEEL
neuro_mf-0.0.5.dist-info/top_level.txt
neuro_mf-0.0.5.dist-info/RECORD
