Metadata-Version: 2.1
Name: neuro_mf
Version: 0.0.5
Summary: iNeuron Model Factory helps us to generate model training and grid search code automatically based 
Home-page: https://github.com/avnyadav/model_factory
Author: Avnish Yadav
License-File: LICENSE
